logical_print.py
ouroboros_text_gen_utils.py
ouroboros_hf_text_generation-1.0.2.dist-info/LICENSE
ouroboros_hf_text_generation-1.0.2.dist-info/METADATA
ouroboros_hf_text_generation-1.0.2.dist-info/WHEEL
ouroboros_hf_text_generation-1.0.2.dist-info/top_level.txt
ouroboros_hf_text_generation-1.0.2.dist-info/RECORD
