Metadata-Version: 2.1
Name: ouroboros_hf_text_generation
Version: 1.0.2
Summary: Simple hugging face text generation utility package with multiple prompt format support and history.
Author: VINUK
License: Apache License
Requires-Python: >=3.10
License-File: LICENSE
Requires-Dist: torch >=2.1.1
Requires-Dist: transformers >=4.37.1
Requires-Dist: accelerate >=0.26.1
Requires-Dist: optimum >=1.16.2
Requires-Dist: rich
